radiomics/__init__.py
radiomics/_cmatrices.cp310-win_amd64.pyd
radiomics/_cshape.cp310-win_amd64.pyd
radiomics/_version.py
radiomics/base.py
radiomics/featureextractor.py
radiomics/firstorder.py
radiomics/generalinfo.py
radiomics/glcm.py
radiomics/gldm.py
radiomics/glrlm.py
radiomics/glszm.py
radiomics/imageoperations.py
radiomics/ngtdm.py
radiomics/shape.py
radiomics/shape2D.py
radiomics/schemas/paramSchema.yaml
radiomics/schemas/schemaFuncs.py
radiomics/scripts/__init__.py
radiomics/scripts/segment.py
radiomics/scripts/voxel.py
pyradiomics_fix-3.0.1.dev4.dist-info/LICENSE.txt
pyradiomics_fix-3.0.1.dev4.dist-info/METADATA
pyradiomics_fix-3.0.1.dev4.dist-info/WHEEL
pyradiomics_fix-3.0.1.dev4.dist-info/entry_points.txt
pyradiomics_fix-3.0.1.dev4.dist-info/top_level.txt
pyradiomics_fix-3.0.1.dev4.dist-info/RECORD
