Metadata-Version: 2.1
Name: pyradiomics-fix
Version: 3.0.1.dev4
Summary: Radiomics features library for python
Home-page: http://github.com/Radiomics/pyradiomics#readme
Author: pyradiomics community
Author-email: pyradiomics@googlegroups.com
License: BSD License
Project-URL: Radiomics.io, https://www.radiomics.io/
Project-URL: Documentation, https://pyradiomics.readthedocs.io/en/latest/index.html
Project-URL: Docker, https://hub.docker.com/r/radiomics/pyradiomics/
Project-URL: Github, https://github.com/Radiomics/pyradiomics
Keywords: radiomics cancerimaging medicalresearch computationalimaging
Classifier: Development Status :: 5 - Production/Stable
Classifier: Environment :: Console
Classifier: Intended Audience :: Developers
Classifier: Intended Audience :: Science/Research
Classifier: License :: OSI Approved :: BSD License
Classifier: Operating System :: OS Independent
Classifier: Programming Language :: C
Classifier: Programming Language :: Python :: 2
Classifier: Programming Language :: Python :: 2.7
Classifier: Programming Language :: Python :: 3.4
Classifier: Programming Language :: Python :: 3.5
Classifier: Programming Language :: Python :: 3.6
Classifier: Topic :: Scientific/Engineering :: Bio-Informatics
License-File: LICENSE.txt
Requires-Dist: numpy (==1.22.1)
Requires-Dist: SimpleITK (==2.1.1.2)
Requires-Dist: PyWavelets (==1.2.)
Requires-Dist: pykwalify (==1.8.0)
Requires-Dist: six (==1.16.0)
